README.rst
setup.py
pyparserchemicalformula/__init__.py
pyparserchemicalformula/contants.py
pyparserchemicalformula/parser.py
pyparserchemicalformula.egg-info/PKG-INFO
pyparserchemicalformula.egg-info/SOURCES.txt
pyparserchemicalformula.egg-info/dependency_links.txt
pyparserchemicalformula.egg-info/entry_points.txt
pyparserchemicalformula.egg-info/top_level.txt